{
  "zk-prefixer": [
    {
      "modifiers": [
        "Ctrl"
      ],
      "key": "Z"
    }
  ],
  "editor:follow-link": [
    {
      "modifiers": [
        "Mod"
      ],
      "key": "B"
    }
  ],
  "daily-notes": [
    {
      "modifiers": [
        "Ctrl"
      ],
      "key": "A"
    }
  ],
  "file-explorer:new-file": [],
  "obsidian-excalidraw-plugin:insert-link": [],
  "obsidian-key-sequence-shortcut:open-key-sequence-palette": [
    {
      "modifiers": [
        "Ctrl"
      ],
      "key": "N"
    }
  ],
  "obsidian-better-command-palette:open-better-commmand-palette": [
    {
      "modifiers": [
        "Mod"
      ],
      "key": "P"
    }
  ],
  "workspace:edit-file-title": [],
  "text-snippets-obsidian:text-snippets": [
    {
      "modifiers": [
        "Ctrl"
      ],
      "key": "O"
    }
  ],
  "file-explorer:new-file-in-new-pane": [],
  "file-explorer:move-file": [
    {
      "modifiers": [
        "Ctrl"
      ],
      "key": "M"
    }
  ],
  "editor:toggle-source": [
    {
      "modifiers": [
        "Ctrl"
      ],
      "key": "I"
    }
  ],
  "editor:toggle-checklist-status": [],
  "file-explorer:open": [
    {
      "modifiers": [
        "Mod"
      ],
      "key": "M"
    }
  ],
  "obsidian-footnotes:insert-footnote": [
    {
      "modifiers": [
        "Ctrl",
        "Shift"
      ],
      "key": "6"
    }
  ],
  "workspace:toggle-pin": [
    {
      "modifiers": [
        "Ctrl"
      ],
      "key": "L"
    }
  ],
  "obsidian-another-quick-switcher:header-search-in-file": [
    {
      "modifiers": [
        "Mod"
      ],
      "key": "F12"
    }
  ],
  "editor:toggle-italics": [],
  "markdown:toggle-preview": [
    {
      "modifiers": [
        "Mod"
      ],
      "key": "I"
    }
  ],
  "editor:insert-wikilink": [
    {
      "modifiers": [
        "Mod"
      ],
      "key": "L"
    }
  ],
  "obsidian-another-quick-switcher:search-command_landmark-search": [
    {
      "modifiers": [
        "Mod"
      ],
      "key": "N"
    }
  ],
  "editor:toggle-bold": [],
  "command-palette:open": [],
  "editor:delete-paragraph": [],
  "editor:fold-all": [
    {
      "modifiers": [
        "Mod",
        "Shift"
      ],
      "key": "-"
    }
  ],
  "editor:unfold-all": [
    {
      "modifiers": [
        "Mod",
        "Shift"
      ],
      "key": "="
    }
  ],
  "workspace:undo-close-pane": [],
  "nldates-obsidian:nlp-date-clean": [
    {
      "modifiers": [
        "Mod",
        "Shift"
      ],
      "key": "T"
    }
  ]
}